{
    "cprule-0": {
        "pcre": "/^configure/",
        "result": "action=configure"
    },
    "cprule0": {
        "pcre": "/^add/",
        "result": "action=add"
    },
    "cprule1": {
        "pcre": "/^list/",
        "result": "action=list"
    },
    "cpruleCatAdd": {
        "pcre": "/^category\\/add$/",
        "result": "action=addcategory"
    },
    "cpruleCatEdit": {
        "pcre": "/^category\\/([0-9]+)\\/edit/",
        "result": "action=editcategory;id=$1"
    },
    "cpruleCatList": {
        "pcre": "/^category\\/([0-9]+)\\/list/",
        "result": "action=list;id=$1"
    },
    "cpruleCategories": {
        "pcre": "/^categories/",
        "result": "action=listcategory"
    },
    "cprule2": {
        "pcre": "/^([0-9]+)\\/edit/",
        "result": "action=edit;id=$1"
    },
    "cprule3": {
        "pcre": "/^([0-9]+)\\/view/",
        "result": "action=view;id=$1"
    },
    "cprule3": {
        "pcre": "/^([0-9]+)\\/delete/",
        "result": "action=delete;id=$1"
    },
    "rule0": {
        "pcre": "/^([0-9]+)\\/view/",
        "result": "action=view;id=$1"
    },
    "rule1": {
        "pcre": "/^([0-9]+)\\/view/",
        "result": "action=view;id=$1"
    },
    "archiveRule": {
        "pcre": "#^archive/([0-9]{2}\\-[0-9]{2}\\-[0-9]{4})#i",
        "result": "action=archive;date=$1"        
    },
    "tagsearchRule": {
        "pcre": "/^tagsearch\\/\\?*t*=*(.*)$/",
        "result": "action=tagsearch;tag=$1"
    }
}