{
    "engine": {
        "siteName" : "phpMyEngine",

        "design" : "default",
        "defaultController" : "index",
        
        "language" : "ru",
        
        "gzip" : false,
        "gziplevel" : 9,
        
        "cache" : false,
        "cacheProfile" : "cacheProfileFilesDS",

        "databaseProfile" : "dbProfileMongoDB",

        "uriType": "asHTMLDocuments"
    },
    "controlPanel": {
            "host": "cp.phpmyengine.dev",
            "virtualController": "ctrlpnl",
            "login": "357126G",
            "password": "swordfish"
    },
    "view": {
        "skin": "coldblue",
        "css": {
            "includeInDocument": false,
            "uniteFiles": true
        }
    },
    "cacheProfileMemcache": {
        "type" : "Memcached",
        "host" : "localhost",
        "port" : 11211,
        "prefix" : "pme1_"
    },
    "cacheProfileFilesDS": {
        "type" : "filesDataStorage"
    },
    
    "dbProfileFilesDS": {
        "type" : "filesDataStorage"
    },
    "dbProfileMongoDB": {
        "type" : "Mongo",
        "host" : "localhost",
        "database" : "pmedb",
        "user" : "357126G",
        "password" : "swordfish"
    }
}